touchtouch/README.MD
touchtouch/__init__.py
touchtouch/requirements.txt
touchtouch/thirdparty.json
touchtouch-0.11.dist-info/LICENSE.rst
touchtouch-0.11.dist-info/METADATA
touchtouch-0.11.dist-info/WHEEL
touchtouch-0.11.dist-info/top_level.txt
touchtouch-0.11.dist-info/RECORD
